pyncd/__init__.py
pyncd/models/__init__.py
pyncd/models/base.py
pyncd/models/louvain.py
pyncd-0.1.0.dist-info/LICENSE
pyncd-0.1.0.dist-info/METADATA
pyncd-0.1.0.dist-info/WHEEL
pyncd-0.1.0.dist-info/top_level.txt
pyncd-0.1.0.dist-info/RECORD
