Metadata-Version: 2.1
Name: pyncd
Version: 0.1.0
Summary: A Python Library for Network Community Detection
Home-page: https://github.com/DengBoCong/pyncd
Author: BoCong Deng
Author-email: bocongdeng@gmail.com
License: BSD-2
Keywords: community detection,deep community detection,deep community detection,deep learning,network analysis,graph mining
Platform: UNKNOWN
Classifier: Intended Audience :: Developers
Classifier: Intended Audience :: Education
Classifier: Intended Audience :: Science/Research
Classifier: Programming Language :: Python :: 3.6
Classifier: Programming Language :: Python :: 3.7
Classifier: Programming Language :: Python :: 3.8
Classifier: Programming Language :: Python :: 3.9
Classifier: Programming Language :: Python :: 3.10
Classifier: License :: OSI Approved :: BSD License
License-File: LICENSE
Requires-Dist: networkx (>=2.8.8)
Requires-Dist: torch (>=1.10.0)
Requires-Dist: numpy (>=1.19.4)
